kimi_cli/CHANGELOG.md
kimi_cli/__init__.py
kimi_cli/agents/default/agent.yaml
kimi_cli/agents/default/sub.yaml
kimi_cli/agents/default/system.md
kimi_cli/agentspec.py
kimi_cli/app.py
kimi_cli/cli.py
kimi_cli/config.py
kimi_cli/constant.py
kimi_cli/exception.py
kimi_cli/llm.py
kimi_cli/metadata.py
kimi_cli/prompts/__init__.py
kimi_cli/prompts/compact.md
kimi_cli/prompts/init.md
kimi_cli/py.typed
kimi_cli/session.py
kimi_cli/share.py
kimi_cli/soul/__init__.py
kimi_cli/soul/agent.py
kimi_cli/soul/approval.py
kimi_cli/soul/compaction.py
kimi_cli/soul/context.py
kimi_cli/soul/denwarenji.py
kimi_cli/soul/kimisoul.py
kimi_cli/soul/message.py
kimi_cli/soul/runtime.py
kimi_cli/soul/toolset.py
kimi_cli/tools/__init__.py
kimi_cli/tools/bash/__init__.py
kimi_cli/tools/bash/bash.md
kimi_cli/tools/bash/cmd.md
kimi_cli/tools/dmail/__init__.py
kimi_cli/tools/dmail/dmail.md
kimi_cli/tools/file/__init__.py
kimi_cli/tools/file/glob.md
kimi_cli/tools/file/glob.py
kimi_cli/tools/file/grep.md
kimi_cli/tools/file/grep.py
kimi_cli/tools/file/patch.md
kimi_cli/tools/file/patch.py
kimi_cli/tools/file/read.md
kimi_cli/tools/file/read.py
kimi_cli/tools/file/replace.md
kimi_cli/tools/file/replace.py
kimi_cli/tools/file/write.md
kimi_cli/tools/file/write.py
kimi_cli/tools/mcp.py
kimi_cli/tools/task/__init__.py
kimi_cli/tools/task/task.md
kimi_cli/tools/test.py
kimi_cli/tools/think/__init__.py
kimi_cli/tools/think/think.md
kimi_cli/tools/todo/__init__.py
kimi_cli/tools/todo/set_todo_list.md
kimi_cli/tools/utils.py
kimi_cli/tools/web/__init__.py
kimi_cli/tools/web/fetch.md
kimi_cli/tools/web/fetch.py
kimi_cli/tools/web/search.md
kimi_cli/tools/web/search.py
kimi_cli/ui/__init__.py
kimi_cli/ui/acp/__init__.py
kimi_cli/ui/print/__init__.py
kimi_cli/ui/print/visualize.py
kimi_cli/ui/shell/__init__.py
kimi_cli/ui/shell/console.py
kimi_cli/ui/shell/debug.py
kimi_cli/ui/shell/keyboard.py
kimi_cli/ui/shell/metacmd.py
kimi_cli/ui/shell/prompt.py
kimi_cli/ui/shell/replay.py
kimi_cli/ui/shell/setup.py
cimi-0.54.1.dist-info/WHEEL
cimi-0.54.1.dist-info/entry_points.txt
cimi-0.54.1.dist-info/METADATA
cimi-0.54.1.dist-info/RECORD
