Metadata-Version: 2.3
Name: cimi
Version: 0.54.1
Summary: KCC - A CLI agent for software engineering tasks (forked from kimi-cli)
Keywords: cli,agent,ai,coding,automation
Author: abhishekbhakat
Author-email: abhishekbhakat <abhishek.bhakat@hotmail.com>
License: Apache-2.0
Classifier: Development Status :: 3 - Alpha
Classifier: Environment :: Console
Classifier: Intended Audience :: Developers
Classifier: License :: OSI Approved :: Apache Software License
Classifier: Operating System :: OS Independent
Classifier: Programming Language :: Python :: 3
Classifier: Programming Language :: Python :: 3.13
Classifier: Topic :: Software Development :: Libraries :: Python Modules
Classifier: Topic :: Utilities
Requires-Dist: agent-client-protocol==0.6.3
Requires-Dist: aiofiles==25.1.0
Requires-Dist: aiohttp==3.13.2
Requires-Dist: typer==0.20.0
Requires-Dist: kosong==0.25.0
Requires-Dist: loguru==0.7.3
Requires-Dist: patch-ng==1.19.0
Requires-Dist: prompt-toolkit==3.0.52
Requires-Dist: pillow==12.0.0
Requires-Dist: pyyaml==6.0.3
Requires-Dist: rich==14.2.0
Requires-Dist: ripgrepy==2.2.0
Requires-Dist: streamingjson==0.0.5
Requires-Dist: trafilatura==2.0.0
Requires-Dist: tenacity==9.1.2
Requires-Dist: fastmcp==2.12.5
Requires-Dist: pydantic==2.12.4
Requires-Dist: httpx[socks]==0.28.1
Requires-Python: >=3.13
